ckip_transformers/__init__.py
ckip_transformers/nlp/__init__.py
ckip_transformers/nlp/driver.py
ckip_transformers/nlp/util.py
ckip_transformers-0.3.4.dist-info/LICENSE
ckip_transformers-0.3.4.dist-info/METADATA
ckip_transformers-0.3.4.dist-info/WHEEL
ckip_transformers-0.3.4.dist-info/top_level.txt
ckip_transformers-0.3.4.dist-info/RECORD
