Metadata-Version: 2.1
Name: ckip-transformers
Version: 0.3.4
Summary: CKIP Transformers
Home-page: https://ckip-transformers.readthedocs.io
Author: Mu Yang
Author-email: emfomy@gmail.com
License: GPL-3.0
Download-URL: https://ckip-transformers.readthedocs.io/tarball/0.3.4
Platform: linux_x86_64
Classifier: Development Status :: 4 - Beta
Classifier: Environment :: Console
Classifier: Programming Language :: Python
Classifier: Programming Language :: Python :: 3
Classifier: Programming Language :: Python :: 3.6
Classifier: Programming Language :: Python :: 3.7
Classifier: Programming Language :: Python :: 3.8
Classifier: Programming Language :: Python :: 3 :: Only
Classifier: License :: OSI Approved :: GNU General Public License v3 (GPLv3)
Classifier: Operating System :: POSIX :: Linux
Classifier: Natural Language :: Chinese (Traditional)
Requires-Python: >=3.6
License-File: LICENSE
Requires-Dist: torch (>=1.5.0)
Requires-Dist: tqdm (>=4.27)
Requires-Dist: transformers (>=3.5.0)
